beaker/__init__.py
beaker/_cluster.py
beaker/_dataset.py
beaker/_experiment.py
beaker/_group.py
beaker/_image.py
beaker/_job.py
beaker/_node.py
beaker/_organization.py
beaker/_queue.py
beaker/_secret.py
beaker/_service_client.py
beaker/_user.py
beaker/_workload.py
beaker/_workspace.py
beaker/beaker_pb2.py
beaker/beaker_pb2.pyi
beaker/beaker_pb2_grpc.py
beaker/client.py
beaker/common.py
beaker/config.py
beaker/exceptions.py
beaker/py.typed
beaker/types.py
beaker/utils.py
beaker/version.py
beaker_py-2.5.1.dist-info/METADATA
beaker_py-2.5.1.dist-info/WHEEL
beaker_py-2.5.1.dist-info/top_level.txt
beaker_py-2.5.1.dist-info/RECORD
