Metadata-Version: 2.4
Name: beaker-py
Version: 2.5.1
Summary: A Python Beaker client
Author-email: Allen Institute for Artificial Intelligence <contact@allenai.org>, Pete Walsh <petew@allenai.org>
Project-URL: Homepage, https://github.com/allenai/beaker
Project-URL: Repository, https://github.com/allenai/beaker
Project-URL: Changelog, https://github.com/allenai/beaker/blob/main/bindings/python/CHANGELOG.md
Project-URL: Documentation, https://beaker-py-docs.allen.ai
Classifier: Intended Audience :: Science/Research
Classifier: Programming Language :: Python :: 3
Classifier: Topic :: Scientific/Engineering :: Artificial Intelligence
Requires-Python: >=3.10
Requires-Dist: requests
Requires-Dist: packaging
Requires-Dist: PyYAML
Requires-Dist: grpcio>=1.70.0
Requires-Dist: protobuf<7.0,>=5.0
Requires-Dist: google-crc32c
Provides-Extra: docker
Requires-Dist: docker<8.0,>=5.0; extra == "docker"
Provides-Extra: dev
Requires-Dist: ruff; extra == "dev"
Requires-Dist: mypy<1.6,>=1.0; extra == "dev"
Requires-Dist: types-requests; extra == "dev"
Requires-Dist: types-cachetools; extra == "dev"
Requires-Dist: types-PyYAML; extra == "dev"
Requires-Dist: types-protobuf; extra == "dev"
Requires-Dist: black<24.0,>=23.0; extra == "dev"
Requires-Dist: isort<5.13,>=5.12; extra == "dev"
Requires-Dist: pytest<8.0; extra == "dev"
Requires-Dist: twine>=1.11.0; extra == "dev"
Requires-Dist: build; extra == "dev"
Requires-Dist: setuptools; extra == "dev"
Requires-Dist: wheel; extra == "dev"
Requires-Dist: petname==2.6; extra == "dev"
Requires-Dist: grpcio-tools; extra == "dev"
Provides-Extra: all
Requires-Dist: beaker-py[dev,docker]; extra == "all"
